gbg_remote_sdk/__init__.py
gbg_remote_sdk/constants.py
gbg_remote_sdk/exceptions.py
gbg_remote_sdk/models.py
gbg_remote_sdk/py.typed
gbg_remote_sdk/sdk.py
gbg_remote_sdk/vendor_files/wsdl.xml
gbg_remote_sdk-0.1.1.dist-info/METADATA
gbg_remote_sdk-0.1.1.dist-info/WHEEL
gbg_remote_sdk-0.1.1.dist-info/top_level.txt
gbg_remote_sdk-0.1.1.dist-info/RECORD
