Metadata-Version: 2.4
Name: gbg-remote-sdk
Version: 0.1.1
Summary: Software Development Kit for the SOAP-based API for Green Button Go Remote Control
Author: Eli Fine
Classifier: Programming Language :: Python :: 3
Classifier: Programming Language :: Python :: 3.12
Classifier: Programming Language :: Python :: 3.13
Requires-Python: >=3.12.7
Requires-Dist: zeep>=4.3.2
Requires-Dist: pydantic>=2.11.7
Requires-Dist: requests>=2.32.5
